{"data":{"id":"c4978adb-899e-4683-a50d-8c48af63a610","run_id":"c21df73b-d32e-46b2-a434-01ff95a730f3","node_id":"019de023-df16-71e3-a9eb-2cf4050373ff","node_persistent_id":"04f47385-8bb6-4b9d-8103-01ad28c6b223","session_id":null,"chat_session_id":null,"event_id":"6e32e01e-722f-4b8b-9372-500b845686d1","name":"Web call","node_type":"action","data":{"room_name":"development_019db77a-0548-741c-9ac8-d713bea1a51f_webcall_cc3ad7a0-0803-4378-8bc1-36ffac1bda02","to_number":"web","from_number":"web","sip_call_id":null,"execution_environment":"development"},"error":null,"status":"succeeded","scope":null,"is_multiple":false,"data_deleted":false,"input_tokens":null,"output_tokens":null,"cached_input_tokens":null,"input":{"room_name":"development_019db77a-0548-741c-9ac8-d713bea1a51f_webcall_cc3ad7a0-0803-4378-8bc1-36ffac1bda02","to_number":"web","from_number":"web","sip_call_id":null,"time.now_utc":"Thursday, April 30, 2026 10:22:16 PM UTC","current.today":"Thursday, April 30, 2026 6:22:16 PM EDT","current.org_id":"019db776-fdcb-7925-8891-a79b1fbc6ea0","current.run_id":"c21df73b-d32e-46b2-a434-01ff95a730f3","current.org_name":"FDE - Andres Navarro","current.use_case_id":"019db77a-0548-741c-9ac8-d713bea1a51f","time.now_asia_dubai":"Friday, May 1, 2026 02:22:16 AM +04","time.now_asia_tokyo":"Friday, May 1, 2026 07:22:16 AM JST","current.use_case_name":"Inbound Carrier Sales New","execution_environment":"development","time.now_europe_paris":"Friday, May 1, 2026 12:22:16 AM CEST","time.now_europe_berlin":"Friday, May 1, 2026 12:22:16 AM CEST","time.now_europe_london":"Thursday, April 30, 2026 11:22:16 PM BST","time.now_america_bogota":"Thursday, April 30, 2026 05:22:16 PM -05","time.now_america_denver":"Thursday, April 30, 2026 04:22:16 PM MDT","time.now_asia_singapore":"Friday, May 1, 2026 06:22:16 AM +08","time.now_america_chicago":"Thursday, April 30, 2026 05:22:16 PM CDT","time.now_america_new_york":"Thursday, April 30, 2026 06:22:16 PM EDT","time.now_australia_sydney":"Friday, May 1, 2026 08:22:16 AM AEST","time.now_america_sao_paulo":"Thursday, April 30, 2026 07:22:16 PM -03","time.now_america_los_angeles":"Thursday, April 30, 2026 03:22:16 PM PDT","time.now_america_mexico_city":"Thursday, April 30, 2026 04:22:16 PM CST","current.execution_environment":"development","use_case_variables.agent_name":"Olivia","use_case_variables.company_name":"Acme Logistics","use_case_variables.fmcsa_web_key":"cdc33e44d693a3a58451898d4ec9df862c65b954","use_case_variables.API_BEARER_TOKEN_":"0df0780c7b29a33010671490e8ff3e318770d5d86a5de704e454ddaf8680c58d ","use_case_variables.negotiation_floor_pct":"0.20","use_case_variables.max_negotiation_rounds":"3"},"timestamp":"2026-04-30T22:22:16.588Z"}}